matmalib/__init__.py
matmalib/calc.py
matmalib/core.py
matmalib/util.py
matmalib/viz.py
matmalib-0.2.6.dist-info/METADATA
matmalib-0.2.6.dist-info/WHEEL
matmalib-0.2.6.dist-info/top_level.txt
matmalib-0.2.6.dist-info/RECORD
