Metadata-Version: 2.4
Name: matmalib
Version: 0.2.6
Summary: Add your description here
Requires-Python: >=3.12
